qualtrics_iat/__init__.py
qualtrics_iat/iat_scorer.py
qualtrics_iat/images_helper.py
qualtrics_iat/qualtrics_tools.py
qualtrics_iat/script_generator.py
qualtrics_iat/web_app.py
qualtrics_iat/web_utils.py
qualtrics_iat/templates/__init__.py
qualtrics_iat-0.2.5.dist-info/LICENSE.txt
qualtrics_iat-0.2.5.dist-info/METADATA
qualtrics_iat-0.2.5.dist-info/WHEEL
qualtrics_iat-0.2.5.dist-info/top_level.txt
qualtrics_iat-0.2.5.dist-info/RECORD
