Metadata-Version: 2.1
Name: qualtrics-iat
Version: 0.2.5
Summary: A toolset for creating and scoring Qualtrics-based IAT experiments
Home-page: https://github.com/ycui1/QualtricsIAT
Author: Yong Cui
Author-email: ycui1@mdanderson.org
License: UNKNOWN
Platform: UNKNOWN
Classifier: Programming Language :: Python :: 3
Classifier: License :: OSI Approved :: MIT License
Classifier: Operating System :: OS Independent
Requires-Python: >=3.9
License-File: LICENSE.txt
